tests/__init__.py
tests/conftest.py
tests/test_aggregation.py
uclales/__init__.py
uclales/check_cross_sections.py
uclales/generate_derived_fields.py
uclales/loader.py
uclales/output/__init__.py
uclales/output/common.py
uclales/output/extraction.py
uclales/plots/__init__.py
uclales/plots/timeseries_statistics.py
uclales_utils-0.1.4.dist-info/METADATA
uclales_utils-0.1.4.dist-info/WHEEL
uclales_utils-0.1.4.dist-info/top_level.txt
uclales_utils-0.1.4.dist-info/RECORD
