Metadata-Version: 2.1
Name: uclales-utils
Version: 0.1.4
Summary: UCLALES utilities
Home-page: https://github.com/leifdenby/uclales-utils
Author: Leif Denby
Author-email: leif@denby.eu
Requires-Dist: xarray
Requires-Dist: netCDF4
Requires-Dist: scipy
Requires-Dist: luigi
Provides-Extra: dev
Requires-Dist: pytest ; extra == 'dev'
Requires-Dist: requests ; extra == 'dev'
Requires-Dist: ipython ; extra == 'dev'
Requires-Dist: pre-commit ; extra == 'dev'
Provides-Extra: test
Requires-Dist: pytest ; extra == 'test'
Requires-Dist: requests ; extra == 'test'
